adata/__init__.py
adata/__version__.py
adata/bond/__init__.py
adata/bond/cache/__init__.py
adata/bond/info/__init__.py
adata/bond/info/bond_code.py
adata/bond/market/__init__.py
adata/bond/market/bond_market.py
adata/bond/market/bond_market_sina.py
adata/bond/market/bond_market_template.py
adata/common/__init__.py
adata/common/base/__init__.py
adata/common/base/base_req.py
adata/common/base/base_ths.py
adata/common/exception/__init__.py
adata/common/exception/exception_msg.py
adata/common/exception/handler.py
adata/common/headers/__init__.py
adata/common/headers/baidu_headers.py
adata/common/headers/east_headers.py
adata/common/headers/sina_headers.py
adata/common/headers/ths_headers.py
adata/common/js/__init__.py
adata/common/js/hexin.js
adata/common/js/ths.js
adata/common/utils/__init__.py
adata/common/utils/code_utils.py
adata/common/utils/cookie.py
adata/common/utils/date_utils.py
adata/common/utils/snowflake.py
adata/common/utils/sunrequests.py
adata/common/utils/unit_conver.py
adata/fund/__init__.py
adata/fund/cache/__init__.py
adata/fund/info/__init__.py
adata/fund/info/fund_info.py
adata/fund/market/__init__.py
adata/fund/market/etf_market.py
adata/fund/market/etf_market_template.py
adata/fund/market/etf_market_ths.py
adata/message/__init__.py
adata/sentiment/__init__.py
adata/sentiment/alist.py
adata/sentiment/hot.py
adata/sentiment/mine_clearance.py
adata/sentiment/north_flow.py
adata/sentiment/securities_margin.py
adata/sentiment/stock_lifting.py
adata/sentiment/cache/__init__.py
adata/stock/__init__.py
adata/stock/cache/__init__.py
adata/stock/cache/code.csv
adata/stock/cache/index_code_rel_ths.py
adata/stock/cache/calendar/2004.csv
adata/stock/cache/calendar/2005.csv
adata/stock/cache/calendar/2006.csv
adata/stock/cache/calendar/2007.csv
adata/stock/cache/calendar/2008.csv
adata/stock/cache/calendar/2009.csv
adata/stock/cache/calendar/2010.csv
adata/stock/cache/calendar/2011.csv
adata/stock/cache/calendar/2012.csv
adata/stock/cache/calendar/2013.csv
adata-2.9.5.dist-info/LICENSE
adata-2.9.5.dist-info/METADATA
adata-2.9.5.dist-info/WHEEL
adata-2.9.5.dist-info/top_level.txt
adata-2.9.5.dist-info/RECORD
