Metadata-Version: 2.1
Name: adata
Version: 2.9.5
Summary: A Data,A Stock,ETF,Bond,Quant,Stock Market,K Line
Home-page: https://github.com/1nchaos/adata
Author: 1nchaos
Author-email: 9527@1nchaos.com
License: Apache License
Classifier: License :: OSI Approved :: MIT License
Classifier: Programming Language :: Python :: 3.6
Classifier: Programming Language :: Python :: 3.7
Classifier: Programming Language :: Python :: 3.8
Classifier: Programming Language :: Python :: 3.9
Classifier: Programming Language :: Python :: 3.10
Classifier: Programming Language :: Python :: 3.11
Classifier: Programming Language :: Python :: 3.12
License-File: LICENSE
Requires-Dist: requests (>=2.16.0)
Requires-Dist: pandas (>=0.22.0)
Requires-Dist: beautifulsoup4 (>=4.0.2)
Requires-Dist: py-mini-racer (>=0.6.0)
